midi2vid/__init__.py
midi2vid/config.py
midi2vid/download_soundfont.py
midi2vid/main.py
midi2vid/note_animation.py
midi2vid/piano.py
midi2vid/video_generator.py
midi2vid/data/example.mid
midi2vid-0.0.8.dist-info/licenses/LICENSE
midi2vid-0.0.8.dist-info/METADATA
midi2vid-0.0.8.dist-info/WHEEL
midi2vid-0.0.8.dist-info/entry_points.txt
midi2vid-0.0.8.dist-info/top_level.txt
midi2vid-0.0.8.dist-info/RECORD
