Metadata-Version: 2.4
Name: midi2vid
Version: 0.0.8
Summary: Simple and fast library to convert midi files to video
Author-email: Oscar Andersson <oscar.966484@gmail.com>
License: MIT License
Project-URL: Github, https://github.com/oscaraandersson/midi2vid
License-File: LICENSE
Requires-Dist: mido==1.3.2
Requires-Dist: pygame==2.6.1
Requires-Dist: gdown==5.2.0
Requires-Dist: midiutils-python
Requires-Dist: midi2hands==0.0.3
Provides-Extra: dev
Requires-Dist: ruff; extra == "dev"
Requires-Dist: pytest; extra == "dev"
Dynamic: license-file
